jmap_engine/__init__.py
jmap_engine/client.py
jmap_engine/email.py
jmap_engine/exceptions.py
jmap_engine/mailbox.py
jmap_engine/session.py
jmap_engine-0.3.0.dist-info/licenses/LICENSE
jmap_engine-0.3.0.dist-info/METADATA
jmap_engine-0.3.0.dist-info/WHEEL
jmap_engine-0.3.0.dist-info/top_level.txt
jmap_engine-0.3.0.dist-info/RECORD
