Metadata-Version: 2.4
Name: jmap-engine
Version: 0.3.0
Summary: Python library for viewing and sending emails through the JMAP protocol
Home-page: https://github.com/cocdeshijie/jmap-engine
Author: cocdeshijie
Author-email: 
Project-URL: Bug Tracker, https://github.com/cocdeshijie/jmap-engine/issues
Project-URL: Documentation, https://github.com/cocdeshijie/jmap-engine#readme
Project-URL: Source Code, https://github.com/cocdeshijie/jmap-engine
Keywords: jmap email rfc8620 rfc8621 mail protocol
Classifier: Development Status :: 3 - Alpha
Classifier: Intended Audience :: Developers
Classifier: Topic :: Communications :: Email
Classifier: Topic :: Software Development :: Libraries :: Python Modules
Classifier: License :: OSI Approved :: MIT License
Classifier: Programming Language :: Python :: 3
Classifier: Programming Language :: Python :: 3.7
Classifier: Programming Language :: Python :: 3.8
Classifier: Programming Language :: Python :: 3.9
Classifier: Programming Language :: Python :: 3.10
Classifier: Programming Language :: Python :: 3.11
Requires-Python: >=3.7
License-File: LICENSE
Requires-Dist: requests>=2.25.0
Provides-Extra: dev
Requires-Dist: pytest>=6.0; extra == "dev"
Requires-Dist: pytest-cov>=2.0; extra == "dev"
Requires-Dist: black>=21.0; extra == "dev"
Requires-Dist: flake8>=3.9; extra == "dev"
Requires-Dist: mypy>=0.910; extra == "dev"
Dynamic: author
Dynamic: classifier
Dynamic: description
Dynamic: description-content-type
Dynamic: home-page
Dynamic: keywords
Dynamic: license-file
Dynamic: project-url
Dynamic: provides-extra
Dynamic: requires-dist
Dynamic: requires-python
Dynamic: summary
